README.md
setup.py
plotguy/__init__.py
plotguy/aggregate.py
plotguy/components.py
plotguy/equity_curves.py
plotguy/signals.py
plotguy.egg-info/PKG-INFO
plotguy.egg-info/SOURCES.txt
plotguy.egg-info/dependency_links.txt
plotguy.egg-info/requires.txt
plotguy.egg-info/top_level.txt