Metadata-Version: 2.1
Name: plotguy
Version: 1.2.9
Summary: Plotguy
Home-page: https://pypi.org/project/plotguy/
Author: Plotguy Team
Author-email: plotguy.info@gmail.com
License: UNKNOWN
Platform: UNKNOWN
Classifier: Programming Language :: Python :: 3
Classifier: Operating System :: OS Independent
